INSTALL.md
LICENSE
MANIFEST.in
README.md
setup.py
pypreprocessor/__init__.py
pypreprocessor.egg-info/PKG-INFO
pypreprocessor.egg-info/SOURCES.txt
pypreprocessor.egg-info/dependency_links.txt
pypreprocessor.egg-info/top_level.txt
tests/__init__.py