Metadata-Version: 1.1
Name: pypreprocessor
Version: 0.7.7
Summary: Run c-style preprocessor directives in python modules
Home-page: https://github.com/interpreters/pypreprocessor
Author: Evan Plaice
Author-email: evanplaice@gmail.com
License: The MIT License (MIT)
